nbtag/__about__.py
nbtag/__init__.py
nbtag/tag_pre_save_hook.py
etc/jupyter/jupyter_server_config.d/nbtag.json
nbtag-0.0.2.dist-info/METADATA
nbtag-0.0.2.dist-info/WHEEL
nbtag-0.0.2.dist-info/RECORD
