Metadata-Version: 2.1
Name: nbtag
Version: 0.0.2
Summary: Set Jupyter notebook cell tags from a special comment
Project-URL: Homepage, https://github.com/indigoviolet/nbtag
Author-email: Venky Iyer <indigoviolet@gmail.com>
Keywords: environments,notebook,reproducible,scholarship,science
Classifier: Intended Audience :: Developers
Classifier: Intended Audience :: Science/Research
Requires-Python: >=3.9
Requires-Dist: nbformat
